llnl_scraper-0.15.0.data/scripts/codegov_compute_hours.py
llnl_scraper-0.15.0.dist-info/licenses/LICENSE
llnl_scraper-0.15.0.dist-info/licenses/NOTICE
scraper/__init__.py
scraper/gen_code_gov_json.py
scraper/util.py
scraper/bitbucket/__init__.py
scraper/code_gov/__init__.py
scraper/code_gov/models.py
scraper/doecode/__init__.py
scraper/github/__init__.py
scraper/github/queryManager.py
scraper/github/util.py
scraper/gitlab/__init__.py
scraper/tfs/__init__.py
scraper/tfs/models.py
llnl_scraper-0.15.0.dist-info/METADATA
llnl_scraper-0.15.0.dist-info/WHEEL
llnl_scraper-0.15.0.dist-info/entry_points.txt
llnl_scraper-0.15.0.dist-info/top_level.txt
llnl_scraper-0.15.0.dist-info/RECORD
