Metadata-Version: 2.4
Name: llnl-scraper
Version: 0.15.0
Summary: Package for extracting software repository metadata
Home-page: https://github.com/llnl/scraper
Author: Ian Lee
Author-email: lee1001@llnl.gov
Classifier: Development Status :: 4 - Beta
Classifier: Intended Audience :: Developers
Classifier: Operating System :: OS Independent
Classifier: Programming Language :: Python
Classifier: Programming Language :: Python :: 3
Classifier: Programming Language :: Python :: 3 :: Only
Classifier: Programming Language :: Python :: 3.6
Classifier: Programming Language :: Python :: 3.7
Classifier: Programming Language :: Python :: 3.8
Classifier: Programming Language :: Python :: 3.9
Classifier: Programming Language :: Python :: 3.10
Classifier: Programming Language :: Python :: Implementation :: CPython
Classifier: Programming Language :: Python :: Implementation :: PyPy
Requires-Python: >=3.6
License-File: LICENSE
License-File: NOTICE
Requires-Dist: github3.py>=2.0.0
Requires-Dist: msrest>=0.6.4
Requires-Dist: python-dateutil>=2.7.3
Requires-Dist: python-gitlab>=1.6.0
Requires-Dist: pytz>=2017.3
Requires-Dist: requests>=2.16
Requires-Dist: setuptools>=24.2.0
Requires-Dist: stashy>=0.3
Requires-Dist: vsts>=0.1.25
Dynamic: author
Dynamic: author-email
Dynamic: classifier
Dynamic: description
Dynamic: description-content-type
Dynamic: home-page
Dynamic: license-file
Dynamic: requires-dist
Dynamic: requires-python
Dynamic: summary
